Metadata-Version: 1.1
Name: scold
Version: 1.0
Summary: Scold it
Home-page: https://github.com/jwalton3141/scold
Author: Jack Walton
Author-email: jwalton3141@gmail.com
License: UNKNOWN
Download-URL: https://github.com/jwalton3141/scold/archive/1.0.tar.gz
Keywords: scold,logging
Platform: UNKNOWN
